backblaze/__init__.py
backblaze/base.py
backblaze/cache.py
backblaze/decorators.py
backblaze/exceptions.py
backblaze/routes.py
backblaze/settings.py
backblaze/utils.py
backblaze/bucket/base.py
backblaze/bucket/awaiting/__init__.py
backblaze/bucket/awaiting/file.py
backblaze/bucket/awaiting/part.py
backblaze/bucket/blocking/__init__.py
backblaze/bucket/blocking/file.py
backblaze/bucket/blocking/part.py
backblaze/http/awaiting.py
backblaze/http/base.py
backblaze/http/blocking.py
backblaze/key/awaiting.py
backblaze/key/base.py
backblaze/key/blocking.py
backblaze/models/auth.py
backblaze/models/bucket.py
backblaze/models/file.py
backblaze/models/key.py
backblaze/tests/shared_vars.py
backblaze/tests/awaiting/client.py
backblaze/tests/awaiting/test_auth.py
backblaze/tests/awaiting/test_bucket.py
backblaze/tests/awaiting/test_file.py
backblaze/tests/awaiting/test_files.py
backblaze/tests/awaiting/test_key.py
backblaze/tests/awaiting/test_misc.py
backblaze/tests/blocking/client.py
backblaze/tests/blocking/test_auth.py
backblaze/tests/blocking/test_bucket.py
backblaze/tests/blocking/test_file.py
backblaze/tests/blocking/test_files.py
backblaze/tests/blocking/test_key.py
backblaze/tests/blocking/test_misc.py
backblaze-0.1.1.dist-info/LICENSE
backblaze-0.1.1.dist-info/METADATA
backblaze-0.1.1.dist-info/WHEEL
backblaze-0.1.1.dist-info/top_level.txt
backblaze-0.1.1.dist-info/RECORD
