Metadata-Version: 2.1
Name: backblaze
Version: 0.1.1
Summary: Wrapper for Backblaze
Home-page: https://backblaze.readthedocs.io/en/latest/
Author: WardPearce
Author-email: wardpearce@protonmail.com
License: GPL-3.0 License
Platform: UNKNOWN
Requires-Python: >=3.6
License-File: LICENSE
